turbo_turtle/README.rst
turbo_turtle/__init__.py
turbo_turtle/_abaqus_wrappers.py
turbo_turtle/_cubit_python.py
turbo_turtle/_cubit_wrappers.py
turbo_turtle/_docs.py
turbo_turtle/_fetch.py
turbo_turtle/_gmsh_python.py
turbo_turtle/_gmsh_wrappers.py
turbo_turtle/_main.py
turbo_turtle/_settings.py
turbo_turtle/_utilities.py
turbo_turtle/_version.py
turbo_turtle/conftest.py
turbo_turtle/geometry_xyplot.py
turbo_turtle/pyproject.toml
turbo_turtle/scons_extensions.py
turbo_turtle/_abaqus_python/_turbo_turtle_plugin.py
turbo_turtle/_abaqus_python/pyproject.toml
turbo_turtle/_abaqus_python/turboTurtleIcon.png
turbo_turtle/_abaqus_python/turbo_turtle_abaqus/__init__.py
turbo_turtle/_abaqus_python/turbo_turtle_abaqus/_abaqus_utilities.py
turbo_turtle/_abaqus_python/turbo_turtle_abaqus/_mixed_settings.py
turbo_turtle/_abaqus_python/turbo_turtle_abaqus/_mixed_utilities.py
turbo_turtle/_abaqus_python/turbo_turtle_abaqus/cylinder.py
turbo_turtle/_abaqus_python/turbo_turtle_abaqus/export.py
turbo_turtle/_abaqus_python/turbo_turtle_abaqus/geometry.py
turbo_turtle/_abaqus_python/turbo_turtle_abaqus/image.py
turbo_turtle/_abaqus_python/turbo_turtle_abaqus/merge.py
turbo_turtle/_abaqus_python/turbo_turtle_abaqus/mesh_module.py
turbo_turtle/_abaqus_python/turbo_turtle_abaqus/parsers.py
turbo_turtle/_abaqus_python/turbo_turtle_abaqus/partition.py
turbo_turtle/_abaqus_python/turbo_turtle_abaqus/sets.py
turbo_turtle/_abaqus_python/turbo_turtle_abaqus/sphere.py
turbo_turtle/_abaqus_python/turbo_turtle_abaqus/test_abaqus_utilities.py
turbo_turtle/_abaqus_python/turbo_turtle_abaqus/test_mixed_utilities.py
turbo_turtle/_abaqus_python/turbo_turtle_abaqus/test_parsers.py
turbo_turtle/_abaqus_python/turbo_turtle_abaqus/test_vertices.py
turbo_turtle/_abaqus_python/turbo_turtle_abaqus/vertices.py
turbo_turtle/_tests/SConstruct
turbo_turtle/_tests/__init__.py
turbo_turtle/_tests/legacy_geometry.py
turbo_turtle/_tests/test_cubit_python.py
turbo_turtle/_tests/test_docs.py
turbo_turtle-1.2.9.dist-info/licenses/LICENSE.txt
turbo_turtle-1.2.9.dist-info/METADATA
turbo_turtle-1.2.9.dist-info/WHEEL
turbo_turtle-1.2.9.dist-info/entry_points.txt
turbo_turtle-1.2.9.dist-info/top_level.txt
turbo_turtle-1.2.9.dist-info/RECORD
