Metadata-Version: 2.4
Name: turbo-turtle
Version: 1.2.9
Summary: Solid body modeling tools for 2D sketched, 2D axisymmetric, and 3D revolved models
Author-email: Kyle Brindley <kbrindley@lanl.gov>, Thomas Roberts <tproberts@lanl.gov>
License-Expression: BSD-3-Clause
Project-URL: homepage, https://github.com/lanl-aea/turbo-turtle
Project-URL: documentation, https://lanl-aea.github.io/turbo-turtle/
Project-URL: repository, https://github.com/lanl-aea/turbo-turtle
Project-URL: changelog, https://lanl-aea.github.io/turbo-turtle/changelog.html
Classifier: Development Status :: 4 - Beta
Classifier: Environment :: Console
Classifier: Intended Audience :: Science/Research
Classifier: Operating System :: OS Independent
Classifier: Programming Language :: Python :: 3
Classifier: Topic :: Scientific/Engineering
Requires-Python: >=3.10
License-File: LICENSE.txt
Requires-Dist: lazy_loader>=0.4
Requires-Dist: matplotlib>=3
Requires-Dist: scons>=4.6
Requires-Dist: waves-workflows>=0.13.0
Provides-Extra: gmsh
Requires-Dist: gmsh; extra == "gmsh"
Dynamic: license-file
